ace_api.py
ace_api-1.0.8.dist-info/METADATA
ace_api-1.0.8.dist-info/WHEEL
ace_api-1.0.8.dist-info/entry_points.txt
ace_api-1.0.8.dist-info/top_level.txt
ace_api-1.0.8.dist-info/RECORD
