Metadata-Version: 2.1
Name: ace-api
Version: 1.0.8
Summary: Analysis Correlation Engine (ACE) API Python Bindings.
Home-page: https://github.com/ace-ecosystem/ACE/_api_package
Author: John Davison
Author-email: unixfreak0037@gmail.com
License: Apache-2.0
Keywords: Cyber Security,Information Security,InfoSec,Detection,Response,SOAR
Platform: UNKNOWN
Classifier: Development Status :: 4 - Beta
Classifier: Intended Audience :: Developers
Classifier: Intended Audience :: Information Technology
Classifier: Intended Audience :: Telecommunications Industry
Classifier: Operating System :: OS Independent
Classifier: License :: OSI Approved :: Apache Software License
Classifier: Programming Language :: Python :: 3 :: Only
Classifier: Programming Language :: Python :: 3
Classifier: Programming Language :: Python :: 3.0
Classifier: Programming Language :: Python :: 3.1
Classifier: Programming Language :: Python :: 3.2
Classifier: Programming Language :: Python :: 3.3
Classifier: Programming Language :: Python :: 3.4
Classifier: Programming Language :: Python :: 3.5
Classifier: Programming Language :: Python :: 3.6
Requires-Dist: tzlocal
Requires-Dist: requests
